ProtY/__init__.py
ProtY/worky_worky.py
ProtY-1.3.dist-info/LICENSE
ProtY-1.3.dist-info/METADATA
ProtY-1.3.dist-info/WHEEL
ProtY-1.3.dist-info/top_level.txt
ProtY-1.3.dist-info/RECORD
