Metadata-Version: 2.1
Name: ProtY
Version: 1.3
Summary: The project is about using a pretrained protein transformer architecture to create embeddings of various proteins, and then performing nonlinear dimensionality reduction on those embeddings to see which kinds of similarities in protein function/structure we can restore
Home-page: https://github.com/uhlarbrigi/PEPTIDE-SEQUENCE-EMBEDDING-AND-CLUSTERING-VISUALIZATION.git
Author: Csapó Bence, Galló Dominik, Uhlár Brigitta
Author-email: uhlarbrigi@gmail.com
Maintainer-email: "Csapó Bence, Galló Dominik, Uhlár Brigitta" <uhlarbrigi@gmail.com>
License: GPL-3.0-only
Project-URL: Homepage, http://your-git.com
Project-URL: Documentation, https://peptide-sequence-embedding-and-clustering-visualization.readthedocs.io/en/latest/
Project-URL: Repository, https://github.com/uhlarbrigi/PEPTIDE-SEQUENCE-EMBEDDING-AND-CLUSTERING-VISUALIZATION.git
Project-URL: Issues, http://your-git.com/issues
Classifier: Development Status :: 1 - Planning
Classifier: Programming Language :: Python :: 3.10
Classifier: Operating System :: OS Independent
Requires-Python: >=3.10
License-File: LICENSE
Requires-Dist: numpy>=1.25.2
Requires-Dist: matplotlib>=3.6.2
Requires-Dist: scikit-learn>=1.1.3
Requires-Dist: scipy>=1.9.3
Requires-Dist: PyWavelets>=1.5.0
Requires-Dist: pandas>=2.0.0
Requires-Dist: emd>=0.6.2
Requires-Dist: nolds>=0.5.2
Requires-Dist: tqdm>=4.64.1
Requires-Dist: pyQt5>=5.15.7
Requires-Dist: fair-esm>=0.1.0
Requires-Dist: sphinx_rtd_theme>=3.0.2
Provides-Extra: docs
Requires-Dist: sphinx; extra == "docs"
Requires-Dist: sphinx_rtd_theme; extra == "docs"
